stegawave/__init__.py
stegawave/_version.py
stegawave/client.py
stegawave/exceptions.py
stegawave/utils.py
stegawave/workflow.py
stegawave/models/__init__.py
stegawave/models/pipeline.py
stegawave-0.2.15.dist-info/METADATA
stegawave-0.2.15.dist-info/WHEEL
stegawave-0.2.15.dist-info/licenses/LICENSE
stegawave-0.2.15.dist-info/RECORD
