Metadata-Version: 2.4
Name: stegawave
Version: 0.2.15
Summary: Python client for the Stegawave media pipeline API
Project-URL: Homepage, https://stegawave.com
Project-URL: Documentation, https://stegawave.com/docs
Project-URL: Source, https://github.com/stegawave/saas-media-backend
Author-email: Stegawave <support@stegawave.com>
License-Expression: MIT
License-File: LICENSE
Keywords: aws,media,stegawave,streaming,video
Classifier: Development Status :: 3 - Alpha
Classifier: Intended Audience :: Developers
Classifier: License :: OSI Approved :: MIT License
Classifier: Programming Language :: Python
Classifier: Programming Language :: Python :: 3
Classifier: Programming Language :: Python :: 3.9
Classifier: Programming Language :: Python :: 3.10
Classifier: Programming Language :: Python :: 3.11
Classifier: Programming Language :: Python :: 3.12
Classifier: Topic :: Internet :: WWW/HTTP
Classifier: Topic :: Multimedia :: Video
Requires-Python: >=3.9
Requires-Dist: pydantic<3,>=2.6
Requires-Dist: requests<3,>=2.32
Provides-Extra: dev
Requires-Dist: pytest-cov<5,>=4.1; extra == 'dev'
Requires-Dist: pytest<9,>=8.2; extra == 'dev'
Requires-Dist: python-dotenv<2,>=1.0; extra == 'dev'
Requires-Dist: responses<0.26,>=0.25; extra == 'dev'
Provides-Extra: docs
Requires-Dist: mkdocs<2,>=1.5; extra == 'docs'
